xszxszxsz/__init__.py
xszxszxsz/main.py
xszxszxsz/资料.py
xszxszxsz-1.0.10.dist-info/LICENSE.txt
xszxszxsz-1.0.10.dist-info/METADATA
xszxszxsz-1.0.10.dist-info/WHEEL
xszxszxsz-1.0.10.dist-info/top_level.txt
xszxszxsz-1.0.10.dist-info/RECORD
