Metadata-Version: 2.1
Name: xszxszxsz
Version: 1.0.10
Summary: just for an stupid exam
Home-page: https://mp.weixin.qq.com/s/9FQ-Tun5FbpBepBAsdY62w
Author: this_is_xm
Author-email: 386697591@qq.com
License: BSD License
Platform: all
Classifier: Intended Audience :: Developers
Classifier: Operating System :: OS Independent
Classifier: Natural Language :: Chinese (Simplified)
Classifier: Programming Language :: Python
Classifier: Programming Language :: Python :: 2
Classifier: Programming Language :: Python :: 2.7
Classifier: Programming Language :: Python :: 3
Classifier: Programming Language :: Python :: 3.5
Classifier: Programming Language :: Python :: 3.6
Classifier: Programming Language :: Python :: 3.7
Classifier: Programming Language :: Python :: 3.8
Classifier: Topic :: Software Development :: Libraries
License-File: LICENSE.txt
